Metadata-Version: 2.1
Name: pyrubrum-continued
Version: 0.2.22
Summary: An intuitive framework for creating Telegram bots
Home-page: https://github.com/hearot/pyrubrum
Author: Hearot
Author-email: gabriel@hearot.it
License: GPLv3
Project-URL: Tracker, https://github.com/hearot/pyrubrum/issues
Project-URL: Source, https://github.com/hearot/pyrubrum
Keywords: bot bots chat messenger mtproto pyrogram python telegram
Classifier: Development Status :: 3 - Alpha
Classifier: Intended Audience :: Developers
Classifier: License :: OSI Approved :: GNU General Public License v3 (GPLv3)
Classifier: Natural Language :: English
Classifier: Operating System :: OS Independent
Classifier: Programming Language :: Python
Classifier: Programming Language :: Python :: 3
Classifier: Programming Language :: Python :: 3.6
Classifier: Programming Language :: Python :: 3.7
Classifier: Programming Language :: Python :: 3.8
Classifier: Programming Language :: Python :: Implementation
Classifier: Programming Language :: Python :: Implementation :: CPython
Classifier: Programming Language :: Python :: Implementation :: PyPy
Classifier: Topic :: Communications
Classifier: Topic :: Communications :: Chat
Classifier: Topic :: Internet
Classifier: Topic :: Software Development :: Libraries
Classifier: Topic :: Software Development :: Libraries :: Application Frameworks
Classifier: Topic :: Software Development :: Libraries :: Python Modules
Classifier: Typing :: Typed
Requires-Python: >=3.6
License-File: LICENSE
License-File: NOTICE
Requires-Dist: pyrogram >=1.0
Provides-Extra: fast
Requires-Dist: orjson ; extra == 'fast'
Requires-Dist: tgcrypto ; extra == 'fast'
